cmdline_vsc-0.1.0.dist-info/METADATA
cmdline_vsc-0.1.0.dist-info/RECORD
cmdline_vsc-0.1.0.dist-info/WHEEL
cmdline_vsc-0.1.0.dist-info/entry_points.txt
cmdline_vsc-0.1.0.dist-info/top_level.txt
vsc/__init__.py
vsc/__main__.py
vsc/stuff.py
vsc/vsc.py
