Metadata-Version: 2.1
Name: cmdline-vsc
Version: 0.1.0
Summary: Python command line application bare bones template.
Home-page: UNKNOWN
Author: Cmitru
Author-email: carmen.mitru@googlemail.com
License: UNKNOWN
Platform: UNKNOWN
